sfcc_connector/__init__.py
sfcc_connector/__main__.py
sfcc_connector/client.py
sfcc_connector/core.py
sfcc_connector/extensions.py
sfcc_connector/queries.py
sfcc_connector/api/__init__.py
sfcc_connector/api/api.py
sfcc_connector-1.0.3.dist-info/LICENSE
sfcc_connector-1.0.3.dist-info/METADATA
sfcc_connector-1.0.3.dist-info/WHEEL
sfcc_connector-1.0.3.dist-info/top_level.txt
sfcc_connector-1.0.3.dist-info/RECORD
