Metadata-Version: 2.1
Name: sfcc-connector
Version: 1.0.3
Summary: Python connector for Salesforce Commerce Cloud via Open Commerce API
Home-page: https://github.com/edro15/sfcc-connector
Author: Erica Pescio
Author-email: edro15@users.noreply.github.com
Maintainer: Erica Pescio
Maintainer-email: edro15@users.noreply.github.com
License: MIT
Keywords: python,salesforce commerce cloud,ocapi,open commerce api,sfcc
Platform: UNKNOWN
Classifier: Development Status :: 4 - Beta
Classifier: Intended Audience :: Developers
Classifier: License :: OSI Approved :: MIT License
Classifier: Natural Language :: English
Classifier: Programming Language :: Python
Classifier: Programming Language :: Python :: 3 :: Only
Classifier: Programming Language :: Python :: 3.6
Classifier: Programming Language :: Python :: 3.7
Classifier: Programming Language :: Python :: 3.8
Classifier: Programming Language :: Python :: 3.9
Requires-Python: >=3.6
License-File: LICENSE
Requires-Dist: api-client (>=1.3.1)
Requires-Dist: pyyaml (>=5.4.1)
Requires-Dist: pydantic (>=1.8.2)
